{
    "ultima_actualizacion": "17:43:41",
    "tablas": {
        "pts": [
            {
                "Rank": 17,
                "Nombre": "Russell Westbrook",
                "Antes": 26514,
                "Hoy": 24,
                "Total": 26538,
                "Diff": "130",
                "Antece": "Dominique Wilkins",
                "Nota": "",
                "game_status": "finished"
            },
            {
                "Rank": 24,
                "Nombre": "DeMar DeRozan",
                "Antes": 25703,
                "Hoy": 20,
                "Total": 25723,
                "Diff": "5",
                "Antece": "Vince Carter",
                "Nota": "",
                "game_status": "finished"
            },
            {
                "Rank": 107,
                "Nombre": "Devin Booker",
                "Antes": 17002,
                "Hoy": 0,
                "Total": 17002,
                "Diff": "66",
                "Antece": "Nikola Vucevic",
                "Nota": "",
                "game_status": "finished"
            },
            {
                "Rank": 115,
                "Nombre": "Mike Conley",
                "Antes": 16597,
                "Hoy": 0,
                "Total": 16597,
                "Diff": "25",
                "Antece": "Jrue Holiday",
                "Nota": "",
                "game_status": "finished"
            },
            {
                "Rank": 192,
                "Nombre": "Harrison Barnes",
                "Antes": 14091,
                "Hoy": 24,
                "Total": 14115,
                "Diff": "40",
                "Antece": "Eric Gordon",
                "Nota": "",
                "game_status": "finished"
            },
            {
                "Rank": 194,
                "Nombre": "Julius Randle",
                "Antes": 14045,
                "Hoy": 21,
                "Total": 14066,
                "Diff": "27",
                "Antece": "Gus Williams",
                "Nota": "",
                "game_status": "finished"
            },
            {
                "Rank": 197,
                "Nombre": "Zach LaVine",
                "Antes": 14028,
                "Hoy": 16,
                "Total": 14044,
                "Diff": "9",
                "Antece": "Jerry Lucas",
                "Nota": "",
                "game_status": "finished"
            }
        ],
        "trb": [
            {
                "Rank": 34,
                "Nombre": "DeAndre Jordan",
                "Antes": 10795,
                "Hoy": 0,
                "Total": 10795,
                "Diff": "21",
                "Antece": "Jack Sikma",
                "Nota": "",
                "game_status": "finished"
            },
            {
                "Rank": 45,
                "Nombre": "Rudy Gobert",
                "Antes": 9934,
                "Hoy": 8,
                "Total": 9942,
                "Diff": "58",
                "Antece": "10000",
                "Nota": "",
                "game_status": "finished"
            },
            {
                "Rank": 60,
                "Nombre": "Russell Westbrook",
                "Antes": 8832,
                "Hoy": 12,
                "Total": 8844,
                "Diff": "130",
                "Antece": "Larry Bird",
                "Nota": "",
                "game_status": "finished"
            },
            {
                "Rank": 121,
                "Nombre": "Domantas Sabonis",
                "Antes": 7015,
                "Hoy": 0,
                "Total": 7015,
                "Diff": "8",
                "Antece": "Detlef Schrempf",
                "Nota": "",
                "game_status": "finished"
            },
            {
                "Rank": 144,
                "Nombre": "Julius Randle",
                "Antes": 6658,
                "Hoy": 3,
                "Total": 6661,
                "Diff": "2",
                "Antece": "Clyde Lovellette",
                "Nota": "",
                "game_status": "finished"
            }
        ],
        "ast": [
            {
                "Rank": 8,
                "Nombre": "Russell Westbrook",
                "Antes": 10086,
                "Hoy": 14,
                "Total": 10100,
                "Diff": "41",
                "Antece": "Magic Johnson",
                "Nota": "",
                "game_status": "finished"
            },
            {
                "Rank": 27,
                "Nombre": "Mike Conley",
                "Antes": 6698,
                "Hoy": 4,
                "Total": 6702,
                "Diff": "9",
                "Antece": "Kevin Johnson",
                "Nota": "",
                "game_status": "finished"
            },
            {
                "Rank": 76,
                "Nombre": "DeMar DeRozan",
                "Antes": 4950,
                "Hoy": 3,
                "Total": 4953,
                "Diff": "29",
                "Antece": "Kevin Durant",
                "Nota": "",
                "game_status": "finished"
            },
            {
                "Rank": 114,
                "Nombre": "Dennis Schroder",
                "Antes": 4205,
                "Hoy": 0,
                "Total": 4205,
                "Diff": "4",
                "Antece": "Michael Adams",
                "Nota": "",
                "game_status": "finished"
            },
            {
                "Rank": 159,
                "Nombre": "Devin Booker",
                "Antes": 3669,
                "Hoy": 0,
                "Total": 3669,
                "Diff": "8",
                "Antece": "D'Angelo Russell",
                "Nota": "",
                "game_status": "finished"
            },
            {
                "Rank": 167,
                "Nombre": "T.J. McConnell",
                "Antes": 3599,
                "Hoy": 3,
                "Total": 3602,
                "Diff": "4",
                "Antece": "Reggie Jackson",
                "Nota": "",
                "game_status": "finished"
            },
            {
                "Rank": 194,
                "Nombre": "De'Aaron Fox",
                "Antes": 3353,
                "Hoy": 7,
                "Total": 3360,
                "Diff": "4",
                "Antece": "Mike Newlin",
                "Nota": "",
                "game_status": "finished"
            },
            {
                "Rank": 209,
                "Nombre": "Domantas Sabonis",
                "Antes": 3203,
                "Hoy": 0,
                "Total": 3203,
                "Diff": "9",
                "Antece": "Vinnie Johnson",
                "Nota": "",
                "game_status": "finished"
            },
            {
                "Rank": 249,
                "Nombre": "Tyrese Haliburton",
                "Antes": 2947,
                "Hoy": 0,
                "Total": 2947,
                "Diff": "15",
                "Antece": "Tom Gola",
                "Nota": "",
                "game_status": "finished"
            }
        ],
        "stl": [
            {
                "Rank": 14,
                "Nombre": "Russell Westbrook",
                "Antes": 1986,
                "Hoy": 2,
                "Total": 1988,
                "Diff": "12",
                "Antece": "2000",
                "Nota": "",
                "game_status": "finished"
            },
            {
                "Rank": 34,
                "Nombre": "Mike Conley",
                "Antes": 1617,
                "Hoy": 0,
                "Total": 1617,
                "Diff": "3",
                "Antece": "Eddie Jones",
                "Nota": "",
                "game_status": "finished"
            },
            {
                "Rank": 97,
                "Nombre": "DeMar DeRozan",
                "Antes": 1200,
                "Hoy": 1,
                "Total": 1201,
                "Diff": "5",
                "Antece": "Reggie Theus",
                "Nota": "",
                "game_status": "finished"
            }
        ],
        "fg3": [
            {
                "Rank": 22,
                "Nombre": "Mike Conley",
                "Antes": 1956,
                "Hoy": 0,
                "Total": 1956,
                "Diff": "22",
                "Antece": "Joe Johnson",
                "Nota": "",
                "game_status": "finished"
            },
            {
                "Rank": 45,
                "Nombre": "Zach LaVine",
                "Antes": 1592,
                "Hoy": 2,
                "Total": 1594,
                "Diff": "6",
                "Antece": "1600",
                "Nota": "",
                "game_status": "finished"
            },
            {
                "Rank": 58,
                "Nombre": "Harrison Barnes",
                "Antes": 1490,
                "Hoy": 4,
                "Total": 1494,
                "Diff": "1",
                "Antece": "Manu Ginobili",
                "Nota": "A tiro de 1",
                "game_status": "finished"
            },
            {
                "Rank": 59,
                "Nombre": "Devin Booker",
                "Antes": 1463,
                "Hoy": 0,
                "Total": 1463,
                "Diff": "31",
                "Antece": "Harrison Barnes",
                "Nota": "",
                "game_status": "finished"
            },
            {
                "Rank": 67,
                "Nombre": "Russell Westbrook",
                "Antes": 1411,
                "Hoy": 2,
                "Total": 1413,
                "Diff": "10",
                "Antece": "Khris Middleton",
                "Nota": "",
                "game_status": "finished"
            },
            {
                "Rank": 100,
                "Nombre": "Joe Ingles",
                "Antes": 1227,
                "Hoy": 0,
                "Total": 1227,
                "Diff": "5",
                "Antece": "Jae Crowder",
                "Nota": "",
                "game_status": "finished"
            },
            {
                "Rank": 115,
                "Nombre": "Anthony Edwards",
                "Antes": 1173,
                "Hoy": 3,
                "Total": 1176,
                "Diff": "2",
                "Antece": "Deron Williams",
                "Nota": "",
                "game_status": "finished"
            },
            {
                "Rank": 137,
                "Nombre": "Dennis Schroder",
                "Antes": 1087,
                "Hoy": 0,
                "Total": 1087,
                "Diff": "3",
                "Antece": "Dana Barros",
                "Nota": "",
                "game_status": "finished"
            },
            {
                "Rank": 160,
                "Nombre": "Jordan Poole",
                "Antes": 1035,
                "Hoy": 0,
                "Total": 1035,
                "Diff": "",
                "Antece": "James Posey",
                "Nota": "Mismo total",
                "game_status": "finished"
            },
            {
                "Rank": 173,
                "Nombre": "Royce O'Neale",
                "Antes": 995,
                "Hoy": 3,
                "Total": 998,
                "Diff": "1",
                "Antece": "Tyler Herro",
                "Nota": "A tiro de 1",
                "game_status": "finished"
            },
            {
                "Rank": 179,
                "Nombre": "Donte DiVincenzo",
                "Antes": 989,
                "Hoy": 0,
                "Total": 989,
                "Diff": "1",
                "Antece": "Joe Dumars",
                "Nota": "A tiro de 1",
                "game_status": "finished"
            },
            {
                "Rank": 182,
                "Nombre": "Doug McDermott",
                "Antes": 986,
                "Hoy": 0,
                "Total": 986,
                "Diff": "2",
                "Antece": "Leandro Barbosa",
                "Nota": "",
                "game_status": "finished"
            },
            {
                "Rank": 186,
                "Nombre": "Malik Monk",
                "Antes": 976,
                "Hoy": 0,
                "Total": 976,
                "Diff": "1",
                "Antece": "Al Harrington",
                "Nota": "A tiro de 1",
                "game_status": "finished"
            },
            {
                "Rank": 205,
                "Nombre": "Dillon Brooks",
                "Antes": 931,
                "Hoy": 2,
                "Total": 933,
                "Diff": "1",
                "Antece": "Chucky Atkins",
                "Nota": "A tiro de 1",
                "game_status": "finished"
            },
            {
                "Rank": 206,
                "Nombre": "Kelly Olynyk",
                "Antes": 925,
                "Hoy": 2,
                "Total": 927,
                "Diff": "6",
                "Antece": "Dillon Brooks",
                "Nota": "",
                "game_status": "finished"
            },
            {
                "Rank": 216,
                "Nombre": "Grayson Allen",
                "Antes": 909,
                "Hoy": 1,
                "Total": 910,
                "Diff": "1",
                "Antece": "Rasual Butler",
                "Nota": "A tiro de 1",
                "game_status": "finished"
            },
            {
                "Rank": 221,
                "Nombre": "Julius Randle",
                "Antes": 890,
                "Hoy": 2,
                "Total": 892,
                "Diff": "1",
                "Antece": "Will Barton",
                "Nota": "A tiro de 1",
                "game_status": "finished"
            },
            {
                "Rank": 237,
                "Nombre": "Tyrese Haliburton",
                "Antes": 856,
                "Hoy": 0,
                "Total": 856,
                "Diff": "3",
                "Antece": "Avery Bradley",
                "Nota": "",
                "game_status": "finished"
            },
            {
                "Rank": 241,
                "Nombre": "De'Aaron Fox",
                "Antes": 849,
                "Hoy": 2,
                "Total": 851,
                "Diff": "1",
                "Antece": "Arron Afflalo",
                "Nota": "A tiro de 1",
                "game_status": "finished"
            }
        ],
        "g": [
            {
                "Rank": 33,
                "Nombre": "Russell Westbrook",
                "Antes": 1260,
                "Hoy": 1,
                "Total": 1261,
                "Diff": "9",
                "Antece": "John Havlicek",
                "Nota": "",
                "game_status": "finished"
            },
            {
                "Rank": 45,
                "Nombre": "DeMar DeRozan",
                "Antes": 1210,
                "Hoy": 1,
                "Total": 1211,
                "Diff": "6",
                "Antece": "Steve Nash",
                "Nota": "",
                "game_status": "finished"
            },
            {
                "Rank": 52,
                "Nombre": "Mike Conley",
                "Antes": 1195,
                "Hoy": 1,
                "Total": 1196,
                "Diff": "",
                "Antece": "Dikembe Mutombo",
                "Nota": "Mismo total",
                "game_status": "finished"
            },
            {
                "Rank": 82,
                "Nombre": "DeAndre Jordan",
                "Antes": 1113,
                "Hoy": 0,
                "Total": 1113,
                "Diff": "3",
                "Antece": "Zach Randolph",
                "Nota": "",
                "game_status": "finished"
            },
            {
                "Rank": 142,
                "Nombre": "Harrison Barnes",
                "Antes": 1015,
                "Hoy": 1,
                "Total": 1016,
                "Diff": "1",
                "Antece": "Tayshaun Prince",
                "Nota": "A tiro de 1",
                "game_status": "finished"
            }
        ],
        "blk": [
            {
                "Rank": 28,
                "Nombre": "Rudy Gobert",
                "Antes": 1753,
                "Hoy": 0,
                "Total": 1753,
                "Diff": "6",
                "Antece": "Serge Ibaka",
                "Nota": "",
                "game_status": "finished"
            },
            {
                "Rank": 37,
                "Nombre": "DeAndre Jordan",
                "Antes": 1568,
                "Hoy": 0,
                "Total": 1568,
                "Diff": "13",
                "Antece": "Benoit Benjamin",
                "Nota": "",
                "game_status": "finished"
            },
            {
                "Rank": 84,
                "Nombre": "Bismack Biyombo",
                "Antes": 1101,
                "Hoy": 0,
                "Total": 1101,
                "Diff": "1",
                "Antece": "Antonio McDyess",
                "Nota": "A tiro de 1",
                "game_status": "finished"
            }
        ]
    },
    "notificaciones": [
        "Russell Westbrook (3 rebounds today) has passed Shawn Kemp and is now ranked 60th all-time in career rebounds with 8,835.",
        "Zach LaVine (8 points today) has passed David West and is now ranked 198th all-time in career points with 14,036.",
        "Harrison Barnes (3 points today) has passed Gus Williams and is now ranked 192nd all-time in career points with 14,094.",
        "Julius Randle (9 points today) has passed Dave DeBusschere and Jerry Lucas and is now ranked 194th all-time in career points with 14,054.",
        "Royce O'Neale (2 three-pointers today) has passed Rafer Alston and is now ranked 173rd all-time in career three-pointers with 997.",
        "Zach LaVine (16 points today) has passed Manu Ginobili and is now ranked 197th all-time in career points with 14,044."
    ],
    "cache_buster": 1765298621
}